panda3s/__init__.py
panda3s/accessors/__init__.py
panda3s/accessors/fusion.py
panda3s/accessors/search.py
panda3s/arrays.py
panda3s/datatypes.py
panda3s-0.1.1.dist-info/METADATA
panda3s-0.1.1.dist-info/WHEEL
panda3s-0.1.1.dist-info/RECORD
