Metadata-Version: 2.1
Name: panda3s
Version: 0.1.1
Summary: Making your Pandas DataFrame a vector database.
License: MIT
Author: RenChu Wang
Author-email: patrick1031wang@gmail.com
Requires-Python: >=3.8,<4.0
Classifier: License :: OSI Approved :: MIT License
Classifier: Programming Language :: Python :: 3
Classifier: Programming Language :: Python :: 3.8
Classifier: Programming Language :: Python :: 3.9
Classifier: Programming Language :: Python :: 3.10
Classifier: Programming Language :: Python :: 3.11
Requires-Dist: faiss-cpu (>=1.7.4,<2.0.0)
Requires-Dist: numpy (>=1.24.3,<2.0.0)
Requires-Dist: pandas (>=1.5,<3.0)
